pynbntnmodem/__init__.py
pynbntnmodem/constants.py
pynbntnmodem/loader.py
pynbntnmodem/modem.py
pynbntnmodem/modems/__init__.py
pynbntnmodem/ntninit.py
pynbntnmodem/structures/__init__.py
pynbntnmodem/structures/edrxconfig.py
pynbntnmodem/structures/message.py
pynbntnmodem/structures/ntnlocation.py
pynbntnmodem/structures/pdpcontext.py
pynbntnmodem/structures/psmconfig.py
pynbntnmodem/structures/reginfo.py
pynbntnmodem/structures/siginfo.py
pynbntnmodem/structures/socketstatus.py
pynbntnmodem/udpsocket.py
pynbntnmodem/utils.py
pynbntnmodem-0.6.16.dist-info/METADATA
pynbntnmodem-0.6.16.dist-info/WHEEL
pynbntnmodem-0.6.16.dist-info/licenses/LICENSE
pynbntnmodem-0.6.16.dist-info/RECORD
