Metadata-Version: 2.4
Name: pynbntnmodem
Version: 0.6.16
Summary: Library for interfacing to Narrowband Non-Terrestrial Network modems using AT commands.
License: Apache2.0
License-File: LICENSE
Author: geoffbrucepayne
Author-email: geoff.bruce-payne@inmarsat.com
Requires-Python: >=3.10,<4.0
Classifier: License :: Other/Proprietary License
Classifier: Programming Language :: Python :: 3
Classifier: Programming Language :: Python :: 3.10
Classifier: Programming Language :: Python :: 3.11
Classifier: Programming Language :: Python :: 3.12
Classifier: Programming Language :: Python :: 3.13
Classifier: Programming Language :: Python :: 3.14
Requires-Dist: pyatcommand (>=0.5.0,<0.6.0)
